{"source/main.ptx": ["frontmatter", "course-documents", "maps", "preps", "loops", "homework", "activities"], "source/misc/syllabus.ptx": ["syllabus"], "source/maps/map-template.ptx": ["mapx"], "source/maps/U26_262_map_1.ptx": ["map1"], "source/maps/U26_262_map_2.ptx": ["map2"], "source/maps/U26_262_map_3.ptx": ["map3"], "source/prepwork/prep-template.ptx": ["prepx"], "source/prepwork/U26_262_prep_1.ptx": ["prep1"], "source/prepwork/U26_262_prep_2.ptx": ["prep2"], "source/prepwork/U26_262_prep_3.ptx": ["prep3"], "source/loops/loop-template.ptx": ["loop-x"], "source/loops/U26_262_loop_1.ptx": ["loop-1"], "source/loops/U26_262_loop_2.ptx": ["loop-2"], "source/loops/U26_262_loop_3.ptx": ["loop-3"], "source/homework/homework-template.ptx": ["hwx-assigned"], "source/homework/U26_262_homework_1.ptx": ["hw1-assigned"], "source/homework/U26_262_homework_2.ptx": ["hw2"], "source/homework/U26_262_homework_3.ptx": ["hw3"], "source/activities/U26_262_activity_0.ptx": ["act0"]}